MiropayPaymentSDK.py
miropay_payment_sdk/__init__.py
miropay_payment_sdk/auth.py
miropay_payment_sdk/client.py
miropay_payment_sdk/constant.py
miropay_payment_sdk/enum.py
miropay_payment_sdk/interface.py
miropay_payment_sdk_test-0.0.14.dist-info/licenses/LICENSE
miropay_payment_sdk_test-0.0.14.dist-info/METADATA
miropay_payment_sdk_test-0.0.14.dist-info/WHEEL
miropay_payment_sdk_test-0.0.14.dist-info/top_level.txt
miropay_payment_sdk_test-0.0.14.dist-info/RECORD
