Metadata-Version: 2.4
Name: miropay-payment-sdk-test
Version: 0.0.14
Summary: Python SDK for MiroPay
Requires-Python: >=3.9
License-File: LICENSE
Requires-Dist: httpx
Requires-Dist: typing
Requires-Dist: cryptography
Dynamic: license-file
